stallyns/__init__.py
stallyns/stallyns.py
stallyns/templates/index.html
stallyns-0.1.2.dist-info/LICENSE
stallyns-0.1.2.dist-info/METADATA
stallyns-0.1.2.dist-info/WHEEL
stallyns-0.1.2.dist-info/entry_points.txt
stallyns-0.1.2.dist-info/top_level.txt
stallyns-0.1.2.dist-info/RECORD
