Metadata-Version: 2.1
Name: stallyns
Version: 0.1.2
Summary: Webapp for user switching with RetroPie and EmulationStation
Home-page: https://github.com/dlawregiets/stallyns
Author: Doug Steigerwald
Author-email: steigerwald.doug@gmail.com
License: Apache License 2.0
Platform: UNKNOWN
Classifier: Programming Language :: Python :: 2.7
Classifier: Programming Language :: Python :: 3
Classifier: License :: OSI Approved :: Apache Software License
Requires-Dist: flask (~=1.0)
